{
  "plugins":[
    [
      "BootstrapContainerPlugin",
      {
        "glossary":{
          "breakpoints":[
            "xs",
            "sm",
            "md",
            "lg",
            "xl"
          ]
        },
        "pk":10078
      },
      [
        [
          "BootstrapRowPlugin",
          {
            "glossary":{
              "hide_plugin":""
            },
            "pk":10079
          },
          [
            [
              "BootstrapColumnPlugin",
              {
                "glossary":{
                  "xs-column-width":"col"
                },
                "pk":10080
              },
              [
                [
                  "ShopOrderViewsPlugin",
                  {
                    "glossary":{
                      "hide_plugin":""
                    },
                    "pk":10081
                  },
                  []
                ]
              ]
            ]
          ]
        ]
      ]
    ]
  ]
}
